pocket_curses/__init__.py
pocket_curses-0.1.dist-info/DESCRIPTION.rst
pocket_curses-0.1.dist-info/METADATA
pocket_curses-0.1.dist-info/RECORD
pocket_curses-0.1.dist-info/WHEEL
pocket_curses-0.1.dist-info/entry_points.txt
pocket_curses-0.1.dist-info/metadata.json
pocket_curses-0.1.dist-info/top_level.txt
