Metadata-Version: 2.0
Name: pocket-curses
Version: 0.1
Summary: An ncurses interface to Pocket API
Home-page: https://github.com/xoolive/pocket_curses/
Author: Xavier Olive
Author-email: git@xoolive.org
License: MIT
Platform: UNKNOWN
Requires-Python: >=3.6
Requires-Dist: appdirs
Requires-Dist: pocket-api
Requires-Dist: pyperclip
